oremi_core/__init__.py
oremi_core/array.py
oremi_core/event.py
oremi_core/event_manager.py
oremi_core/json.py
oremi_core/logger.py
oremi_core/network.py
oremi_core/process.py
oremi_core/timer.py
oremi_core/vars.py
oremi_core/wsclient.py
oremi_core/wsjsonrpc_client.py
oremi_core/wsjsonrpc_server.py
oremi_core/wsserver.py
oremi_core-2.5.3.dist-info/LICENSE
oremi_core-2.5.3.dist-info/LICENSE_HEADER.txt
oremi_core-2.5.3.dist-info/METADATA
oremi_core-2.5.3.dist-info/WHEEL
oremi_core-2.5.3.dist-info/RECORD
