Metadata-Version: 2.1
Name: oremi-core
Version: 2.5.3
Summary: The cornerstone of the Oremi ecosystem
Home-page: https://gitlab.com/demsking/oremi-core
License: Apache-2.0
Keywords: oremi,core,utils
Author: Sébastien Demanou
Author-email: demsking@gmail.com
Requires-Python: >=3.10,<4.0
Classifier: Development Status :: 2 - Pre-Alpha
Classifier: Environment :: Console
Classifier: Intended Audience :: Developers
Classifier: License :: OSI Approved :: Apache Software License
Classifier: Operating System :: POSIX :: Linux
Classifier: Programming Language :: Python :: 3
Classifier: Programming Language :: Python :: 3.10
Classifier: Programming Language :: Python :: 3.11
Classifier: Programming Language :: Python :: 3.12
Classifier: Topic :: Software Development :: Libraries :: Python Modules
Classifier: Topic :: Software Development :: Localization
Requires-Dist: coloredlogs (>=15.0.1,<16.0.0)
Requires-Dist: python-dateutil (>=2.8.2,<3.0.0)
Requires-Dist: websockets (>=14.1,<15.0)
Project-URL: Documentation, https://gitlab.com/demsking/oremi-core/-/blob/main/README.md
Project-URL: Repository, https://gitlab.com/demsking/oremi-core
Project-URL: Say Thanks!, https://www.buymeacoffee.com/demsking
Project-URL: Source, https://gitlab.com/demsking/oremi-core
Project-URL: Tracker, https://gitlab.com/demsking/oremi-core/-/issues
